openvr/__init__.py
openvr/color_cube_actor.py
openvr/gl_renderer.py
openvr/libopenvr_api_32.dll
openvr/libopenvr_api_32.dylib
openvr/libopenvr_api_32.so
openvr/libopenvr_api_64.dll
openvr/libopenvr_api_64.so
openvr/tracked_devices_actor.py
openvr/version.py
openvr/error_code/__init__.py
openvr/glframework/__init__.py
openvr/glframework/cyglfw3_app.py
openvr/glframework/glfw_app.py
openvr/glframework/glmatrix.py
openvr/glframework/glut_app.py
openvr/glframework/qt5_app.py
openvr/glframework/qt_pyside_app.py
openvr/glframework/sdl_app.py
openvr/glframework/wx_app.py
openvr-2.5.102.dist-info/licenses/LICENSE
openvr-2.5.102.dist-info/METADATA
openvr-2.5.102.dist-info/WHEEL
openvr-2.5.102.dist-info/top_level.txt
openvr-2.5.102.dist-info/RECORD
